graphql_utilities/__init__.py
graphql_utilities/decorators.py
graphql_utilities/directives.py
graphql_utilities/exceptions.py
graphql_utilities/execution.py
graphql_utilities/helpers.py
graphql_utilities/utilities.py
graphql_utilities/validate.py
graphql_utilities/visitor.py
tests/__init__.py
tests/helpers.py
tests/schema.py
tests/test_cost_analysis.py
tests/test_decorators.py
tests/test_depth_analysis.py
graphql_utilities-0.4.0.dist-info/LICENSE
graphql_utilities-0.4.0.dist-info/METADATA
graphql_utilities-0.4.0.dist-info/WHEEL
graphql_utilities-0.4.0.dist-info/top_level.txt
graphql_utilities-0.4.0.dist-info/RECORD
