Metadata-Version: 2.1
Name: graphql-utilities
Version: 0.4.0
Summary: Collection of utilities, middleware, decorators for graphql-core>=3.0
Home-page: https://github.com/melvinkcx/graphql-utilities
Author: Melvin Koh
Author-email: melvinkcx@gmail.com
License: UNKNOWN
Platform: UNKNOWN
Classifier: Development Status :: 3 - Alpha
Classifier: Environment :: Web Environment
Classifier: Intended Audience :: Developers
Classifier: License :: OSI Approved :: MIT License
Classifier: Operating System :: OS Independent
Classifier: Programming Language :: Python
Classifier: Programming Language :: Python :: 3
Classifier: Programming Language :: Python :: 3.7
Classifier: Programming Language :: Python :: 3.6
Classifier: Programming Language :: Python :: 3.5
Classifier: Topic :: Software Development :: Libraries
Requires-Python: >=3.6,<4
Requires-Dist: graphql-core (>=3.0)
Provides-Extra: dev
Requires-Dist: pytest (<6,>=5.3.4) ; extra == 'dev'
Requires-Dist: flake8 (<4,>=3.7.9) ; extra == 'dev'
Requires-Dist: pytest-describe (<1,>=0.12) ; extra == 'dev'
Requires-Dist: django (<3,>=1.11) ; extra == 'dev'
Requires-Dist: sphinx (<3,>=2.4.1) ; extra == 'dev'
Requires-Dist: sphinx-rtd-theme (<1,>=0.4.3) ; extra == 'dev'
